dataclass_documenter/__init__.py
dataclass_documenter/block_meta.py
dataclass_documenter/dataclass_documenter.py
dataclass_documenter/main.py
dataclass_documenter/typing.py
dataclass_documenter/version.py
dataclass_documenter-2025.10.dist-info/METADATA
dataclass_documenter-2025.10.dist-info/WHEEL
dataclass_documenter-2025.10.dist-info/entry_points.txt
dataclass_documenter-2025.10.dist-info/licenses/LICENSE.txt
dataclass_documenter-2025.10.dist-info/RECORD
