Metadata-Version: 2.4
Name: Dataclass_Documenter
Version: 2025.10
Summary: Generate commented YAML input files and markdown documentation from dataclasses.
Project-URL: Homepage, https://gitlab.inria.fr/jrye/dataclass-documenter
Project-URL: Source, https://gitlab.inria.fr/jrye/dataclass-documenter.git
Project-URL: Documentation, https://jrye.gitlabpages.inria.fr/dataclass-documenter
Project-URL: Issues, https://gitlab.inria.fr/jrye/dataclass-documenter/issues
Author-email: Jan-Michael Rye <jan-michael.rye@inria.fr>
License: MIT License
License-File: LICENSE.txt
Classifier: License :: OSI Approved :: MIT License
Classifier: Operating System :: OS Independent
Classifier: Programming Language :: Python :: 3
Requires-Python: >=3.8
Requires-Dist: docstring-parser
Requires-Dist: pyyaml
Provides-Extra: test
Requires-Dist: coverage; extra == 'test'
